{
    "version": "0.5.31",
    "description": "Lightweight, cross-platform database client",
    "homepage": "https://dbxio.com",
    "license": "AGPL-3.0-only",
    "architecture": {
        "64bit": {
            "url": "https://github.com/t8y2/dbx/releases/download/v0.5.31/DBX_0.5.31_x64-portable.zip",
            "hash": "5f14c8f3434d005cd4b17fab8b6b3b5d773f44ff0be1a438cbc80a05f5480bb0"
        }
    },
    "shortcuts": [
        [
            "DBX.exe",
            "DBX"
        ]
    ],
    "persist": "data",
    "checkver": {
        "github": "https://github.com/t8y2/dbx"
    },
    "autoupdate": {
        "architecture": {
            "64bit": {
                "url": "https://github.com/t8y2/dbx/releases/download/v$version/DBX_$version_x64-portable.zip"
            }
        }
    }
}
