{
    "version": "0.3.39",
    "description": "All-in-One Desktop Agent Skills Utility",
    "homepage": "https://www.luochang.ink/skill-zoo",
    "license": "MIT",
    "architecture": {
        "64bit": {
            "url": "https://github.com/luochang212/skill-zoo/releases/download/v0.3.39/Skill-Zoo-v0.3.39-Windows-Portable.zip",
            "hash": "a16fb22db23639e62152b9d68866ad1724da8c2aef8670b5836e8caab2eb58c1",
            "extract_dir": "skill-zoo-portable"
        }
    },
    "shortcuts": [
        [
            "skill-zoo.exe",
            "Skill-Zoo"
        ]
    ],
    "checkver": {
        "github": "https://github.com/luochang212/skill-zoo"
    },
    "autoupdate": {
        "architecture": {
            "64bit": {
                "url": "https://github.com/luochang212/skill-zoo/releases/download/v$version/Skill-Zoo-v$version-Windows-Portable.zip"
            }
        }
    }
}
