{
    "version": "1.3.1",
    "description": "A modern cross-platform terminal emulator with a built-in autonomous AI Agent",
    "homepage": "https://uniterm.net",
    "license": "Apache-2.0",
    "architecture": {
        "64bit": {
            "url": "https://github.com/ys-ll/uniterm/releases/download/v1.3.1/uniterm-windows-amd64-portable-v1.3.1.zip",
            "hash": "3a49811c7b65bc9a52aa08e2341769acda098c4faeeddf5ea08f883117958f39"
        }
    },
    "shortcuts": [
        [
            "uniTerm.exe",
            "uniTerm"
        ]
    ],
    "post_install": "New-Item -Path \"$env:APPDATA\\uniTerm\" -Target \"$dir\\data\" -ItemType Junction -Force | Out-Null",
    "post_uninstall": "Remove-Item \"$env:APPDATA\\uniTerm\" -Force -Recurse",
    "persist": "data",
    "checkver": {
        "github": "https://github.com/ys-ll/uniterm"
    },
    "autoupdate": {
        "architecture": {
            "64bit": {
                "url": "https://github.com/ys-ll/uniterm/releases/download/v$version/uniterm-windows-amd64-portable-v$version.zip"
            }
        }
    }
}
